invenio/__init__.py
invenio/version.py
invenio-3.4.1.dist-info/AUTHORS.rst
invenio-3.4.1.dist-info/LICENSE
invenio-3.4.1.dist-info/METADATA
invenio-3.4.1.dist-info/WHEEL
invenio-3.4.1.dist-info/top_level.txt
invenio-3.4.1.dist-info/RECORD
