Metadata-Version: 2.1
Name: invenio
Version: 3.4.1
Summary: Invenio Digital Library Framework.
Home-page: https://github.com/inveniosoftware/invenio
Author: CERN
Author-email: info@inveniosoftware.org
License: MIT
Keywords: Invenio digital library framework
Platform: any
Classifier: Environment :: Web Environment
Classifier: Intended Audience :: Developers
Classifier: License :: OSI Approved :: MIT License
Classifier: Operating System :: OS Independent
Classifier: Programming Language :: Python
Classifier: Topic :: Internet :: WWW/HTTP :: Dynamic Content
Classifier: Topic :: Software Development :: Libraries :: Python Modules
Classifier: Programming Language :: Python :: 3
Classifier: Programming Language :: Python :: 3.6
Classifier: Programming Language :: Python :: 3.7
Classifier: Programming Language :: Python :: 3.8
Classifier: Development Status :: 5 - Production/Stable
Requires-Dist: invenio-app (<1.4.0,>=1.3.1)
Requires-Dist: invenio-base (<1.3.0,>=1.2.4)
Requires-Dist: invenio-cache (<1.2.0,>=1.1.0)
Requires-Dist: invenio-celery (<1.3.0,>=1.2.2)
Requires-Dist: invenio-config (<1.1.0,>=1.0.3)
Requires-Dist: invenio-i18n (<1.4.0,>=1.3.0)
Provides-Extra: all
Requires-Dist: invenio-admin (<1.4.0,>=1.3.0) ; extra == 'all'
Requires-Dist: invenio-assets (<1.3.0,>=1.2.5) ; extra == 'all'
Requires-Dist: invenio-formatter (<1.2.0,>=1.1.0) ; extra == 'all'
Requires-Dist: invenio-logging (<1.4.0,>=1.3.0) ; extra == 'all'
Requires-Dist: invenio-mail (<1.1.0,>=1.0.2) ; extra == 'all'
Requires-Dist: invenio-rest (<1.3.0,>=1.2.3) ; extra == 'all'
Requires-Dist: invenio-theme (<1.4.0,>=1.3.5) ; extra == 'all'
Requires-Dist: invenio-access (<1.5.0,>=1.4.1) ; extra == 'all'
Requires-Dist: invenio-accounts (<1.5.0,>=1.4.3) ; extra == 'all'
Requires-Dist: invenio-oauth2server (<1.4.0,>=1.3.2) ; extra == 'all'
Requires-Dist: invenio-oauthclient (<1.5.0,>=1.4.0) ; extra == 'all'
Requires-Dist: invenio-userprofiles (<1.3.0,>=1.2.1) ; extra == 'all'
Requires-Dist: invenio-indexer (<1.3.0,>=1.2.0) ; extra == 'all'
Requires-Dist: invenio-jsonschemas (<1.2.0,>=1.1.1) ; extra == 'all'
Requires-Dist: invenio-oaiserver (<1.3.0,>=1.2.0) ; extra == 'all'
Requires-Dist: invenio-pidstore (<1.3.0,>=1.2.1) ; extra == 'all'
Requires-Dist: invenio-records-rest (<1.9.0,>=1.8.0) ; extra == 'all'
Requires-Dist: invenio-records-ui (<1.3.0,>=1.2.0) ; extra == 'all'
Requires-Dist: invenio-records (<1.6.0,>=1.4.0) ; extra == 'all'
Requires-Dist: invenio-search-ui (<2.1.0,>=2.0.0) ; extra == 'all'
Requires-Dist: invenio-files-rest (<1.3.0,>=1.2.0) ; extra == 'all'
Requires-Dist: invenio-iiif (<1.2.0,>=1.1.0) ; extra == 'all'
Requires-Dist: invenio-previewer (<1.4.0,>=1.3.2) ; extra == 'all'
Requires-Dist: invenio-records-files (<1.3.0,>=1.2.1) ; extra == 'all'
Requires-Dist: Sphinx (<4,>=3) ; extra == 'all'
Requires-Dist: pytest-invenio (<1.5.0,>=1.4.0) ; extra == 'all'
Provides-Extra: auth
Requires-Dist: invenio-access (<1.5.0,>=1.4.1) ; extra == 'auth'
Requires-Dist: invenio-accounts (<1.5.0,>=1.4.3) ; extra == 'auth'
Requires-Dist: invenio-oauth2server (<1.4.0,>=1.3.2) ; extra == 'auth'
Requires-Dist: invenio-oauthclient (<1.5.0,>=1.4.0) ; extra == 'auth'
Requires-Dist: invenio-userprofiles (<1.3.0,>=1.2.1) ; extra == 'auth'
Provides-Extra: base
Requires-Dist: invenio-admin (<1.4.0,>=1.3.0) ; extra == 'base'
Requires-Dist: invenio-assets (<1.3.0,>=1.2.5) ; extra == 'base'
Requires-Dist: invenio-formatter (<1.2.0,>=1.1.0) ; extra == 'base'
Requires-Dist: invenio-logging (<1.4.0,>=1.3.0) ; extra == 'base'
Requires-Dist: invenio-mail (<1.1.0,>=1.0.2) ; extra == 'base'
Requires-Dist: invenio-rest (<1.3.0,>=1.2.3) ; extra == 'base'
Requires-Dist: invenio-theme (<1.4.0,>=1.3.5) ; extra == 'base'
Provides-Extra: docs
Requires-Dist: Sphinx (<4,>=3) ; extra == 'docs'
Provides-Extra: elasticsearch5
Requires-Dist: invenio-search[elasticsearch5] (<1.5.0,>=1.4.1) ; extra == 'elasticsearch5'
Provides-Extra: elasticsearch6
Requires-Dist: invenio-search[elasticsearch6] (<1.5.0,>=1.4.1) ; extra == 'elasticsearch6'
Provides-Extra: elasticsearch7
Requires-Dist: invenio-search[elasticsearch7] (<1.5.0,>=1.4.1) ; extra == 'elasticsearch7'
Provides-Extra: files
Requires-Dist: invenio-files-rest (<1.3.0,>=1.2.0) ; extra == 'files'
Requires-Dist: invenio-iiif (<1.2.0,>=1.1.0) ; extra == 'files'
Requires-Dist: invenio-previewer (<1.4.0,>=1.3.2) ; extra == 'files'
Requires-Dist: invenio-records-files (<1.3.0,>=1.2.1) ; extra == 'files'
Provides-Extra: metadata
Requires-Dist: invenio-indexer (<1.3.0,>=1.2.0) ; extra == 'metadata'
Requires-Dist: invenio-jsonschemas (<1.2.0,>=1.1.1) ; extra == 'metadata'
Requires-Dist: invenio-oaiserver (<1.3.0,>=1.2.0) ; extra == 'metadata'
Requires-Dist: invenio-pidstore (<1.3.0,>=1.2.1) ; extra == 'metadata'
Requires-Dist: invenio-records-rest (<1.9.0,>=1.8.0) ; extra == 'metadata'
Requires-Dist: invenio-records-ui (<1.3.0,>=1.2.0) ; extra == 'metadata'
Requires-Dist: invenio-records (<1.6.0,>=1.4.0) ; extra == 'metadata'
Requires-Dist: invenio-search-ui (<2.1.0,>=2.0.0) ; extra == 'metadata'
Provides-Extra: mysql
Requires-Dist: invenio-db[mysql,versioning] (<1.1.0,>=1.0.8) ; extra == 'mysql'
Provides-Extra: postgresql
Requires-Dist: invenio-db[postgresql,versioning] (<1.1.0,>=1.0.8) ; extra == 'postgresql'
Provides-Extra: sqlite
Requires-Dist: invenio-db[versioning] (<1.1.0,>=1.0.8) ; extra == 'sqlite'
Provides-Extra: tests
Requires-Dist: pytest-invenio (<1.5.0,>=1.4.0) ; extra == 'tests'
